Workbook

Sheet Mode d'emploi
A1: Cotonou Box · Saint-Valentin 2027 — Calcul des coûts et des prix
A3: Comment l'utiliser
A4: 1. Dans chaque onglet de coffret, remplacez les montants en BLEU sur fond jaune par vos vrais prix d'achat.
A5: 2. Les montants déjà saisis sont des EXEMPLES (estimations) pour montrer le format : ils ne sont pas des prix réels.
A6: 3. Tout le reste (en noir) se calcule tout seul : coût total, marge, prix conseillé.
A7: 4. Dans l'onglet « Récap », indiquez combien de coffrets vous pensez vendre : vous voyez le budget d'achat et le bénéfice.
A9: Repères
A10: • Coefficient = prix de vente ÷ coût. Visez au moins 1,8 à 2 (le prix couvre le coût + votre travail + les imprévus).
A11: • Marge = ce qu'il vous reste par coffret, avant votre temps de travail.
A12: • Pensez au transport France → Bénin et à la douane si vous achetez des produits en France.
A14: Légende
A15: Texte bleu sur fond jaune = à remplir · Texte noir = calculé automatiquement

Sheet Petite Attention
A1: Petite Attention — Saint-Valentin 2027
A2: Montants en bleu = exemples à remplacer par vos vrais prix d'achat.
A4: Article | B4: Exemple / où l’acheter | C4: Coût unitaire | D4: Quantité | E4: Total
A5: Contenu du coffret
A6: Une douceur | B6: Chocolats ou friandises | C6: 2500 | D6: 1 | E6: =C6*D6 -> 2500
A7: Un mini soin | B7: Baume à lèvres, mini crème | C7: 2000 | D7: 1 | E7: =C7*D7 -> 2000
A8: Une bougie | B8: Petite bougie parfumée | C8: 2000 | D8: 1 | E8: =C8*D8 -> 2000
A9: Emballage et frais
A10: Boîte cadeau | B10: Boîte rigide avec couvercle | C10: 1500 | D10: 1 | E10: =C10*D10 -> 1500
A11: Ruban, papier de soie | B11: Ruban satin + papier | C11: 500 | D11: 1 | E11: =C11*D11 -> 500
A12: Décor (pétales, cœur…) | B12: Pétales séchés, autocollant cœur | C12: 300 | D12: 1 | E12: =C12*D12 -> 300
A13: Carte écrite à la main | B13: Carte + enveloppe | C13: 300 | D13: 1 | E13: =C13*D13 -> 300
A14: Transport France → Bénin / douane | B14: Par coffret (0 si tout est acheté au Bénin) | C14: 0 | D14: 1 | E14: =C14*D14 -> 0
A15: Livraison au client (si offerte) | B15: 0 si le client la paie à part | C15: 0 | D15: 1 | E15: =C15*D15 -> 0
A17: Coût total par coffret | E17: =SUM(E6:E8)+SUM(E10:E15) -> 9100
A18: Prix de vente | E18: 15000
A19: Marge par coffret | E19: =E18-E17 -> 5900
A20: Marge en % | E20: =IF(E18=0,0,E19/E18) -> 0.39333333
A21: Coefficient (prix ÷ coût) | E21: =IF(E17=0,0,E18/E17) -> 1.6483516
A22: Coefficient visé | E22: 2
A23: Prix conseillé (coût × coefficient visé) | E23: =ROUND(E17*E22,-3) -> 18000

Sheet Coffret Amour
A1: Coffret Amour — Saint-Valentin 2027
A2: Montants en bleu = exemples à remplacer par vos vrais prix d'achat.
A4: Article | B4: Exemple / où l’acheter | C4: Coût unitaire | D4: Quantité | E4: Total
A5: Contenu du coffret
A6: Des douceurs | B6: Chocolats, biscuits | C6: 3500 | D6: 1 | E6: =C6*D6 -> 3500
A7: Un soin de grande maison | B7: Mini Rituals / Yves Rocher | C7: 5000 | D7: 1 | E7: =C7*D7 -> 5000
A8: Une création artisanale | B8: Bracelet en perles, porte-clés | C8: 3000 | D8: 1 | E8: =C8*D8 -> 3000
A9: Emballage et frais
A10: Boîte cadeau | B10: Boîte rigide avec couvercle | C10: 2500 | D10: 1 | E10: =C10*D10 -> 2500
A11: Ruban, papier de soie | B11: Ruban satin + papier | C11: 700 | D11: 1 | E11: =C11*D11 -> 700
A12: Décor (pétales, cœur…) | B12: Pétales séchés, autocollant cœur | C12: 500 | D12: 1 | E12: =C12*D12 -> 500
A13: Carte écrite à la main | B13: Carte + enveloppe | C13: 300 | D13: 1 | E13: =C13*D13 -> 300
A14: Transport France → Bénin / douane | B14: Par coffret (0 si tout est acheté au Bénin) | C14: 0 | D14: 1 | E14: =C14*D14 -> 0
A15: Livraison au client (si offerte) | B15: 0 si le client la paie à part | C15: 0 | D15: 1 | E15: =C15*D15 -> 0
A17: Coût total par coffret | E17: =SUM(E6:E8)+SUM(E10:E15) -> 15500
A18: Prix de vente | E18: 25000
A19: Marge par coffret | E19: =E18-E17 -> 9500
A20: Marge en % | E20: =IF(E18=0,0,E19/E18) -> 0.38
A21: Coefficient (prix ÷ coût) | E21: =IF(E17=0,0,E18/E17) -> 1.6129032
A22: Coefficient visé | E22: 2
A23: Prix conseillé (coût × coefficient visé) | E23: =ROUND(E17*E22,-3) -> 31000

Sheet Coffret Prestige
A1: Coffret Prestige — Saint-Valentin 2027
A2: Montants en bleu = exemples à remplacer par vos vrais prix d'achat.
A4: Article | B4: Exemple / où l’acheter | C4: Coût unitaire | D4: Quantité | E4: Total
A5: Contenu du coffret
A6: Un coffret de soins de luxe | B6: Coffret cadeau Rituals | C6: 15000 | D6: 1 | E6: =C6*D6 -> 15000
A7: Un parfum | B7: Mini parfum / brume Sephora | C7: 6000 | D7: 1 | E7: =C7*D7 -> 6000
A8: Un bijou d’artisan | B8: Bijou en laiton ou perles | C8: 5000 | D8: 1 | E8: =C8*D8 -> 5000
A9: Des douceurs fines | B9: Chocolats fins | C9: 4000 | D9: 1 | E9: =C9*D9 -> 4000
A10: Emballage et frais
A11: Boîte cadeau | B11: Boîte rigide avec couvercle | C11: 4000 | D11: 1 | E11: =C11*D11 -> 4000
A12: Ruban, papier de soie | B12: Ruban satin + papier | C12: 1000 | D12: 1 | E12: =C12*D12 -> 1000
A13: Décor (pétales, cœur…) | B13: Pétales séchés, autocollant cœur | C13: 800 | D13: 1 | E13: =C13*D13 -> 800
A14: Carte écrite à la main | B14: Carte + enveloppe | C14: 300 | D14: 1 | E14: =C14*D14 -> 300
A15: Transport France → Bénin / douane | B15: Par coffret (0 si tout est acheté au Bénin) | C15: 0 | D15: 1 | E15: =C15*D15 -> 0
A16: Livraison au client (si offerte) | B16: 0 si le client la paie à part | C16: 0 | D16: 1 | E16: =C16*D16 -> 0
A18: Coût total par coffret | E18: =SUM(E6:E9)+SUM(E11:E16) -> 36100
A19: Prix de vente | E19: 45000
A20: Marge par coffret | E20: =E19-E18 -> 8900
A21: Marge en % | E21: =IF(E19=0,0,E20/E19) -> 0.19777778
A22: Coefficient (prix ÷ coût) | E22: =IF(E18=0,0,E19/E18) -> 1.2465374
A23: Coefficient visé | E23: 2
A24: Prix conseillé (coût × coefficient visé) | E24: =ROUND(E18*E23,-3) -> 72000

Sheet Récap
A1: Récapitulatif — Saint-Valentin 2027
A3: Coffret | B3: Coût | C3: Prix de vente | D3: Marge / coffret | E3: Coffrets prévus | F3: Budget d’achat | G3: Chiffre d’affaires | H3: Bénéfice
A4: Petite Attention | B4: ='Petite Attention'!E17 -> 9100 | C4: ='Petite Attention'!E18 -> 15000 | D4: ='Petite Attention'!E19 -> 5900 | E4: 10 | F4: =B4*E4 -> 91000 | G4: =C4*E4 -> 150000 | H4: =D4*E4 -> 59000
A5: Coffret Amour | B5: ='Coffret Amour'!E17 -> 15500 | C5: ='Coffret Amour'!E18 -> 25000 | D5: ='Coffret Amour'!E19 -> 9500 | E5: 10 | F5: =B5*E5 -> 155000 | G5: =C5*E5 -> 250000 | H5: =D5*E5 -> 95000
A6: Coffret Prestige | B6: ='Coffret Prestige'!E18 -> 36100 | C6: ='Coffret Prestige'!E19 -> 45000 | D6: ='Coffret Prestige'!E20 -> 8900 | E6: 10 | F6: =B6*E6 -> 361000 | G6: =C6*E6 -> 450000 | H6: =D6*E6 -> 89000
A7: Total | E7: =SUM(E4:E6) -> 30 | F7: =SUM(F4:F6) -> 607000 | G7: =SUM(G4:G6) -> 850000 | H7: =SUM(H4:H6) -> 243000
A9: « Coffrets prévus » (en bleu) : remplacez 10 par votre estimation. Le budget d'achat est ce qu'il faut avancer si vous achetez tout avant les commandes.
